{
  "todo": [
    {
      "id": "1",
      "title": "Officia consequatur ",
      "description": "Sit odio quam dolor"
    },
    {
      "id": "2",
      "title": "Hyalo",
      "description": "Hyalo Hyalo"
    },
    {
      "id": "5",
      "title": "Cillum nemo molestia",
      "description": "Pariatur Aliqua Id"
    },
    {
      "id": "5",
      "title": "Delectus dolorem ve",
      "description": "Quidem dolore recusa"
    },
    {
      "id": "28",
      "title": "Todo 5",
      "description": "Mama Paga DAdadadad"
    }
  ]
}